.gitignore
LICENSE.txt
MANIFEST.in
requirements.txt
setup.py
doc/.gitignore
doc/Makefile
doc/conf.py
doc/index.rst
doc/make.bat
doc/serverfiles.rst
serverfiles/__init__.py
serverfiles.egg-info/PKG-INFO
serverfiles.egg-info/SOURCES.txt
serverfiles.egg-info/dependency_links.txt
serverfiles.egg-info/not-zip-safe
serverfiles.egg-info/requires.txt
serverfiles.egg-info/top_level.txt
tests/__init__.py
tests/test_serverfiles.py