Metadata-Version: 1.0
Name: serverfiles
Version: 0.2.1
Summary: An utility that accesses files on a HTTP server and stores them locally for reuse.
Home-page: UNKNOWN
Author: Bioinformatics Laboratory, FRI UL
Author-email: marko.toplak@fri.uni-lj.si
License: UNKNOWN
Platform: UNKNOWN
